mkapi
mkapi/core
mkapi/plugins
mkapi/templates
mkapi/theme
