Metadata-Version: 1.2
Name: mkapi-git-pull
Version: 1.0.12.post1
Summary: Fork of mkapi since poetry fails with git + python verson constraint
Home-page: https://mkapi.daizutabi.net
Author: daizutabi
Author-email: daizutabi@gmail.com
License: MIT
Platform: UNKNOWN
Classifier: Development Status :: 4 - Beta
Classifier: License :: OSI Approved :: MIT License
Classifier: Operating System :: OS Independent
Classifier: Programming Language :: Python
Classifier: Programming Language :: Python :: 3
Classifier: Programming Language :: Python :: 3.7
Classifier: Programming Language :: Python :: 3.8
Classifier: Topic :: Documentation
Requires-Python: >=3.7
